toraman/__init__.py
toraman/bilingualfile.py
toraman/language_codes.py
toraman/sfhelper.py
toraman/sourcefile.py
toraman/translationmemory.py
toraman/utils.py
toraman/version.py
toraman-0.4.2.dist-info/LICENSE
toraman-0.4.2.dist-info/METADATA
toraman-0.4.2.dist-info/WHEEL
toraman-0.4.2.dist-info/top_level.txt
toraman-0.4.2.dist-info/RECORD
