Metadata-Version: 2.1
Name: toraman
Version: 0.4.2
Summary: A computer-assisted translation tool package
Home-page: https://github.com/csengor/toraman-py
Author: Çağatay Onur Şengör
Author-email: contact@csengor.com
License: UNKNOWN
Keywords: CAT,computer-assisted translation,computer-aided translation,translation,free-to-use
Platform: UNKNOWN
Classifier: Development Status :: 3 - Alpha
Classifier: License :: OSI Approved :: MIT License
Classifier: Operating System :: OS Independent
Classifier: Programming Language :: Python :: 3
Requires-Dist: lxml
Requires-Dist: python-levenshtein
Requires-Dist: regex
